codeme/__init__.py
codeme/__main__.py
codeme/code.py
codeme-0.1.9.dist-info/METADATA
codeme-0.1.9.dist-info/WHEEL
codeme-0.1.9.dist-info/top_level.txt
codeme-0.1.9.dist-info/RECORD
