Metadata-Version: 2.1
Name: codeme
Version: 0.1.9
Summary: CodeMe - Automatic Python Coder
Author: Neetish Singh(AAYS Anaytics)
Author-email: <neetishsingh97@gmail.com>
Keywords: python,pyspark,spark,ingestion,data,dataframe,analysis,schema,pandas,chatgpt,auto,bot
Classifier: Development Status :: 1 - Planning
Classifier: Intended Audience :: Developers
Classifier: Programming Language :: Python :: 3
Classifier: Operating System :: Unix
Classifier: Operating System :: MacOS :: MacOS X
Classifier: Operating System :: Microsoft :: Windows
Requires-Dist: requests
